synkit/__init__.py
synkit/examples.py
synkit/CRN/__init__.py
synkit/CRN/DAG/__init__.py
synkit/CRN/DAG/crn.py
synkit/CRN/DAG/dag.py
synkit/CRN/DAG/dcrn.py
synkit/CRN/DAG/mod_crn.py
synkit/CRN/DAG/sf.py
synkit/CRN/DAG/target_dag.py
synkit/CRN/Hypergraph/__init__.py
synkit/CRN/Hypergraph/backend.py
synkit/CRN/Hypergraph/conversion.py
synkit/CRN/Hypergraph/dag.py
synkit/CRN/Hypergraph/hyperedge.py
synkit/CRN/Hypergraph/hypergraph.py
synkit/CRN/Hypergraph/rxn.py
synkit/CRN/Path/__init__.py
synkit/CRN/Path/realizability.py
synkit/CRN/Petri/__init__.py
synkit/CRN/Petri/analyzer.py
synkit/CRN/Petri/net.py
synkit/CRN/Petri/persistence.py
synkit/CRN/Petri/semiflows.py
synkit/CRN/Petri/structure.py
synkit/CRN/Props/__init__.py
synkit/CRN/Props/deficiency.py
synkit/CRN/Props/injectivity.py
synkit/CRN/Props/stoich.py
synkit/CRN/Props/thermo.py
synkit/CRN/Props/utils.py
synkit/CRN/Stochastic/__init__.py
synkit/CRN/Topo/__init__.py
synkit/CRN/Topo/automorphism.py
synkit/CRN/Topo/canon.py
synkit/CRN/Topo/wl_canon.py
synkit/CRN/dev_crn/__init__.py
synkit/CRN/dev_crn/constants.py
synkit/CRN/dev_crn/crn_formula.py
synkit/CRN/dev_crn/enumerator.py
synkit/CRN/dev_crn/exceptions.py
synkit/CRN/dev_crn/explorer.py
synkit/CRN/dev_crn/helpers.py
synkit/CRN/dev_crn/motif.py
synkit/CRN/dev_crn/network.py
synkit/CRN/dev_crn/pathway.py
synkit/CRN/dev_crn/properties.py
synkit/CRN/dev_crn/reaction.py
synkit/CRN/dev_crn/utils.py
synkit/CRN/dev_crn/viz.py
synkit/CRN/dev_crn/configs/__init__.py
synkit/CRN/dev_crn/configs/loader.py
synkit/CRN/dev_crn/configs/models.py
synkit/CRN/viz/crn_vis.py
synkit/Chem/__init__.py
synkit/Chem/utils.py
synkit/Chem/Cluster/__init__.py
synkit/Chem/Cluster/butina.py
synkit/Chem/Fingerprint/__init__.py
synkit/Chem/Fingerprint/fp_calculator.py
synkit/Chem/Fingerprint/smiles_featurizer.py
synkit/Chem/Fingerprint/transformation_fp.py
synkit/Chem/Molecule/__init__.py
synkit/Chem/Molecule/atom_features.py
synkit/Chem/Molecule/descriptors.py
synkit/Chem/Molecule/formula.py
synkit-1.1.1.dist-info/METADATA
synkit-1.1.1.dist-info/WHEEL
synkit-1.1.1.dist-info/licenses/LICENSE
synkit-1.1.1.dist-info/RECORD
