Metadata-Version: 2.4
Name: synkit
Version: 1.1.1
Summary: Utility for reaction modeling using graph grammar
Project-URL: homepage, https://github.com/TieuLongPhan/SynKit
Project-URL: source, https://github.com/TieuLongPhan/SynKit
Project-URL: issues, https://github.com/TieuLongPhan/SynKit/issues
Project-URL: documentation, https://tieulongphan.github.io/SynKit/
Author-email: Tieu Long Phan <tieu@bioinf.uni-leipzig.de>
License: MIT
License-File: LICENSE
Classifier: License :: OSI Approved :: MIT License
Classifier: Operating System :: OS Independent
Classifier: Programming Language :: Python :: 3
Requires-Python: >=3.11
Requires-Dist: networkx>=3.3
Requires-Dist: pandas>=1.5.3
Requires-Dist: rdkit>=2025.3.1
Requires-Dist: regex>=2024.11.6
Requires-Dist: requests>=2.32.3
Requires-Dist: scikit-learn>=1.4.0
Requires-Dist: seaborn>=0.13.2
Provides-Extra: all
Requires-Dist: numpy>=2.2.0; extra == 'all'
Requires-Dist: torch>=2.2.0; extra == 'all'
Provides-Extra: docs
Requires-Dist: sphinx-rtd-theme; extra == 'docs'
Requires-Dist: sphinx>=6.0; extra == 'docs'
Requires-Dist: sphinxcontrib-bibtex; extra == 'docs'
